openplantbook/__init__.py
pyopenplantbook/__init__.py
pyopenplantbook-0.0.4.dist-info/LICENSE
pyopenplantbook-0.0.4.dist-info/METADATA
pyopenplantbook-0.0.4.dist-info/WHEEL
pyopenplantbook-0.0.4.dist-info/top_level.txt
pyopenplantbook-0.0.4.dist-info/RECORD
