Metadata-Version: 2.1
Name: pyopenplantbook
Version: 0.0.4
Summary: OpenPlantbook provides access to the OpenPlantbook API
Home-page: https://github.com/Olen/python-openplantbook
License: UNKNOWN
Project-URL: Documentation, https://open.plantbook.io/
Platform: UNKNOWN
Requires-Dist: aiohttp
